mplang/__init__.py
mplang/cli.py
mplang/cli_guide.md
mplang/py.typed
mplang/backends/__init__.py
mplang/backends/bfv_impl.py
mplang/backends/channel.py
mplang/backends/crypto_impl.py
mplang/backends/field_impl.py
mplang/backends/func_impl.py
mplang/backends/phe_impl.py
mplang/backends/simp_design.md
mplang/backends/spu_impl.py
mplang/backends/spu_state.py
mplang/backends/store_impl.py
mplang/backends/table_impl.py
mplang/backends/tee_impl.py
mplang/backends/tensor_impl.py
mplang/backends/simp_driver/__init__.py
mplang/backends/simp_driver/http.py
mplang/backends/simp_driver/mem.py
mplang/backends/simp_driver/ops.py
mplang/backends/simp_driver/state.py
mplang/backends/simp_driver/values.py
mplang/backends/simp_worker/__init__.py
mplang/backends/simp_worker/http.py
mplang/backends/simp_worker/mem.py
mplang/backends/simp_worker/ops.py
mplang/backends/simp_worker/state.py
mplang/dialects/__init__.py
mplang/dialects/bfv.py
mplang/dialects/crypto.py
mplang/dialects/dtypes.py
mplang/dialects/field.py
mplang/dialects/func.py
mplang/dialects/phe.py
mplang/dialects/simp.py
mplang/dialects/spu.py
mplang/dialects/store.py
mplang/dialects/table.py
mplang/dialects/tee.py
mplang/dialects/tensor.py
mplang/edsl/README.md
mplang/edsl/__init__.py
mplang/edsl/context.py
mplang/edsl/graph.py
mplang/edsl/jit.py
mplang/edsl/object.py
mplang/edsl/primitive.py
mplang/edsl/printer.py
mplang/edsl/program.py
mplang/edsl/registry.py
mplang/edsl/serde.py
mplang/edsl/tracer.py
mplang/edsl/typing.py
mplang/kernels/Makefile
mplang/kernels/__init__.py
mplang/kernels/gf128.cpp
mplang/kernels/ldpc.cpp
mplang/kernels/okvs.cpp
mplang/kernels/okvs_opt.cpp
mplang/kernels/py_kernels.py
mplang/libs/collective.py
mplang/libs/device/__init__.py
mplang/libs/device/api.py
mplang/libs/device/cluster.py
mplang/libs/ml/__init__.py
mplang/libs/ml/sgb.py
mplang/libs/mpc/__init__.py
mplang/libs/mpc/_utils.py
mplang/libs/mpc/analytics/__init__.py
mplang/libs/mpc/analytics/aggregation.py
mplang_nightly-0.1.dev280.dist-info/METADATA
mplang_nightly-0.1.dev280.dist-info/WHEEL
mplang_nightly-0.1.dev280.dist-info/entry_points.txt
mplang_nightly-0.1.dev280.dist-info/licenses/LICENSE
mplang_nightly-0.1.dev280.dist-info/RECORD
