Metadata-Version: 2.4
Name: mplang-nightly
Version: 0.1.dev280
Summary: Multi-Party Programming Language
Author-email: SecretFlow Team <secretflow-contact@service.alipay.com>
License:                                  Apache License
License-File: LICENSE
Requires-Python: <3.13,>=3.11
Requires-Dist: coincurve>=20.0.0
Requires-Dist: cryptography>=43.0.0
Requires-Dist: duckdb>=1.0.0
Requires-Dist: fastapi
Requires-Dist: flax>=0.12.0
Requires-Dist: httpx<1.0.0,>=0.27.0
Requires-Dist: jax[cpu]==0.8.0
Requires-Dist: lightphe<0.1.0,>=0.0.15
Requires-Dist: numpy!=2.4.0,>=2.0.0
Requires-Dist: pandas>=2.0.0
Requires-Dist: protobuf<6.0,>=5.0
Requires-Dist: pyarrow>=14.0.0
Requires-Dist: pyyaml>=6.0
Requires-Dist: spu>=0.10.0.dev20251211
Requires-Dist: sqlglot>=23.0.0
Requires-Dist: tenseal==0.3.16
Requires-Dist: typing-extensions
Requires-Dist: uvicorn[standard]
